{
  "Fish Hoek": {
    "100": "",
    "102": "",
    "104": "",
    "106": "",
    "108": "",
    "110": "",
    "112": "",
    "114": "",
    "116": "",
    "118": "",
    "120": "",
    "122": "",
    "124": "",
    "126": "",
    "128": "",
    "130": "",
    "132": "",
    "134": "",
    "136": "",
    "138": "",
    "140": "",
    "142": "",
    "144": "",
    "146": "",
    "148": "",
    "150": "",
    "152": "",
    "154": "",
    "156": "",
    "158": ""
  },
  "Kalk Bay": {
    "100": "04:49",
    "102": "05:14",
    "104": "05:59",
    "106": "06:19",
    "108": "06:39",
    "110": "06:59",
    "112": "07:19",
    "114": "07:39",
    "116": "07:59",
    "118": "08:14",
    "120": "08:39",
    "122": "08:59",
    "124": "09:19",
    "126": "09:39",
    "128": "10:19",
    "130": "11:19",
    "132": "12:19",
    "134": "13:19",
    "136": "14:19",
    "138": "15:19",
    "140": "15:39",
    "142": "15:59",
    "144": "16:19",
    "146": "16:39",
    "148": "16:59",
    "150": "17:19",
    "152": "17:39",
    "154": "17:59",
    "156": "18:19",
    "158": "18:39"
  },
  "St James": {
    "100": "04:51",
    "102": "05:16",
    "104": "06:01",
    "106": "06:21",
    "108": "06:41",
    "110": "07:01",
    "112": "07:21",
    "114": "07:41",
    "116": "08:01",
    "118": "08:16",
    "120": "08:41",
    "122": "09:01",
    "124": "09:21",
    "126": "09:41",
    "128": "10:21",
    "130": "11:21",
    "132": "12:21",
    "134": "13:21",
    "136": "14:21",
    "138": "15:21",
    "140": "15:41",
    "142": "16:01",
    "144": "16:21",
    "146": "16:41",
    "148": "17:01",
    "150": "17:21",
    "152": "17:41",
    "154": "18:01",
    "156": "18:21",
    "158": "18:41"
  },
  "Muizenberg": {
    "100": "04:54",
    "102": "05:19",
    "104": "06:04",
    "106": "06:24",
    "108": "06:44",
    "110": "07:04",
    "112": "07:24",
    "114": "07:44",
    "116": "08:04",
    "118": "08:19",
    "120": "08:44",
    "122": "09:04",
    "124": "09:24",
    "126": "09:44",
    "128": "10:24",
    "130": "11:24",
    "132": "12:24",
    "134": "13:24",
    "136": "14:24",
    "138": "15:24",
    "140": "15:44",
    "142": "16:04",
    "144": "16:24",
    "146": "16:44",
    "148": "17:04",
    "150": "17:24",
    "152": "17:44",
    "154": "18:04",
    "156": "18:24",
    "158": "18:44"
  },
  "False Bay": {
    "100": "04:56",
    "102": "05:21",
    "104": "06:06",
    "106": "06:26",
    "108": "06:46",
    "110": "07:06",
    "112": "07:26",
    "114": "07:46",
    "116": "08:06",
    "118": "08:21",
    "120": "08:46",
    "122": "09:06",
    "124": "09:26",
    "126": "09:46",
    "128": "10:26",
    "130": "11:26",
    "132": "12:26",
    "134": "13:26",
    "136": "14:26",
    "138": "15:26",
    "140": "15:46",
    "142": "16:06",
    "144": "16:26",
    "146": "16:46",
    "148": "17:06",
    "150": "17:26",
    "152": "17:46",
    "154": "18:06",
    "156": "18:26",
    "158": "18:46"
  },
  "Lakeside": {
    "100": "04:58",
    "102": "05:23",
    "104": "06:08",
    "106": "06:28",
    "108": "06:48",
    "110": "07:08",
    "112": "07:28",
    "114": "07:48",
    "116": "08:08",
    "118": "08:23",
    "120": "08:48",
    "122": "09:08",
    "124": "09:28",
    "126": "09:48",
    "128": "10:28",
    "130": "11:28",
    "132": "12:28",
    "134": "13:28",
    "136": "14:28",
    "138": "15:28",
    "140": "15:48",
    "142": "16:08",
    "144": "16:28",
    "146": "16:48",
    "148": "17:08",
    "150": "17:28",
    "152": "17:48",
    "154": "18:08",
    "156": "18:28",
    "158": "18:48"
  },
  "Steenberg": {
    "100": "05:00",
    "102": "05:25",
    "104": "06:10",
    "106": "06:30",
    "108": "06:50",
    "110": "07:10",
    "112": "07:30",
    "114": "07:50",
    "116": "08:10",
    "118": "08:25",
    "120": "08:50",
    "122": "09:10",
    "124": "09:30",
    "126": "09:50",
    "128": "10:30",
    "130": "11:30",
    "132": "12:30",
    "134": "13:30",
    "136": "14:30",
    "138": "15:30",
    "140": "15:50",
    "142": "16:10",
    "144": "16:30",
    "146": "16:50",
    "148": "17:10",
    "150": "17:30",
    "152": "17:50",
    "154": "18:10",
    "156": "18:30",
    "158": "18:50"
  },
  "Retreat": {
    "100": "05:03",
    "102": "05:28",
    "104": "06:13",
    "106": "06:33",
    "108": "06:53",
    "110": "07:13",
    "112": "07:33",
    "114": "07:53",
    "116": "08:13",
    "118": "08:28",
    "120": "08:53",
    "122": "09:13",
    "124": "09:33",
    "126": "09:53",
    "128": "10:33",
    "130": "11:33",
    "132": "12:33",
    "134": "13:33",
    "136": "14:33",
    "138": "15:33",
    "140": "15:53",
    "142": "16:13",
    "144": "16:33",
    "146": "16:53",
    "148": "17:13",
    "150": "17:33",
    "152": "17:53",
    "154": "18:13",
    "156": "18:33",
    "158": "18:53"
  },
  "Heathfield": {
    "100": "05:06",
    "102": "05:31",
    "104": "06:16",
    "106": "06:36",
    "108": "06:56",
    "110": "07:16",
    "112": "07:36",
    "114": "07:56",
    "116": "08:16",
    "118": "08:31",
    "120": "08:56",
    "122": "09:16",
    "124": "09:36",
    "126": "09:56",
    "128": "10:36",
    "130": "11:36",
    "132": "12:36",
    "134": "13:36",
    "136": "14:36",
    "138": "15:36",
    "140": "15:56",
    "142": "16:16",
    "144": "16:36",
    "146": "16:56",
    "148": "17:16",
    "150": "17:36",
    "152": "17:56",
    "154": "18:16",
    "156": "18:36",
    "158": "18:56"
  },
  "Dieprivier": {
    "100": "05:09",
    "102": "05:34",
    "104": "06:19",
    "106": "06:39",
    "108": "06:59",
    "110": "07:19",
    "112": "07:39",
    "114": "07:59",
    "116": "08:19",
    "118": "08:34",
    "120": "08:59",
    "122": "09:19",
    "124": "09:39",
    "126": "09:59",
    "128": "10:39",
    "130": "11:39",
    "132": "12:39",
    "134": "13:39",
    "136": "14:39",
    "138": "15:39",
    "140": "15:59",
    "142": "16:19",
    "144": "16:39",
    "146": "16:59",
    "148": "17:19",
    "150": "17:39",
    "152": "17:59",
    "154": "18:19",
    "156": "18:39",
    "158": "18:59"
  },
  "Steurhof": {
    "100": "05:12",
    "102": "05:37",
    "104": "06:22",
    "106": "06:42",
    "108": "07:02",
    "110": "07:22",
    "112": "07:42",
    "114": "08:02",
    "116": "08:22",
    "118": "08:37",
    "120": "09:02",
    "122": "09:22",
    "124": "09:42",
    "126": "10:02",
    "128": "10:42",
    "130": "11:42",
    "132": "12:42",
    "134": "13:42",
    "136": "14:42",
    "138": "15:42",
    "140": "16:02",
    "142": "16:22",
    "144": "16:42",
    "146": "17:02",
    "148": "17:22",
    "150": "17:42",
    "152": "18:02",
    "154": "18:22",
    "156": "18:42",
    "158": "19:02"
  },
  "Plumstead": {
    "100": "05:14",
    "102": "05:39",
    "104": "06:24",
    "106": "06:44",
    "108": "07:04",
    "110": "07:24",
    "112": "07:44",
    "114": "08:04",
    "116": "08:24",
    "118": "08:39",
    "120": "09:04",
    "122": "09:24",
    "124": "09:44",
    "126": "10:04",
    "128": "10:44",
    "130": "11:44",
    "132": "12:44",
    "134": "13:44",
    "136": "14:44",
    "138": "15:44",
    "140": "16:04",
    "142": "16:24",
    "144": "16:44",
    "146": "17:04",
    "148": "17:24",
    "150": "17:44",
    "152": "18:04",
    "154": "18:24",
    "156": "18:44",
    "158": "19:04"
  },
  "Wittebome": {
    "100": "05:16",
    "102": "05:41",
    "104": "06:26",
    "106": "06:46",
    "108": "07:06",
    "110": "07:26",
    "112": "07:46",
    "114": "08:06",
    "116": "08:26",
    "118": "08:41",
    "120": "09:06",
    "122": "09:26",
    "124": "09:46",
    "126": "10:06",
    "128": "10:46",
    "130": "11:46",
    "132": "12:46",
    "134": "13:46",
    "136": "14:46",
    "138": "15:46",
    "140": "16:06",
    "142": "16:26",
    "144": "16:46",
    "146": "17:06",
    "148": "17:26",
    "150": "17:46",
    "152": "18:06",
    "154": "18:26",
    "156": "18:46",
    "158": "19:06"
  },
  "Wynberg": {
    "100": "05:18",
    "102": "05:43",
    "104": "06:28",
    "106": "06:48",
    "108": "07:08",
    "110": "07:28",
    "112": "07:48",
    "114": "08:08",
    "116": "08:28",
    "118": "08:43",
    "120": "09:08",
    "122": "09:28",
    "124": "09:48",
    "126": "10:08",
    "128": "10:48",
    "130": "11:48",
    "132": "12:48",
    "134": "13:48",
    "136": "14:48",
    "138": "15:48",
    "140": "16:08",
    "142": "16:28",
    "144": "16:48",
    "146": "17:08",
    "148": "17:28",
    "150": "17:48",
    "152": "18:08",
    "154": "18:28",
    "156": "18:48",
    "158": "19:08"
  },
  "Kenilworth": {
    "100": "05:20",
    "102": "05:45",
    "104": "06:30",
    "106": "06:50",
    "108": "07:10",
    "110": "07:30",
    "112": "07:50",
    "114": "08:10",
    "116": "08:30",
    "118": "08:45",
    "120": "09:10",
    "122": "09:30",
    "124": "09:50",
    "126": "10:10",
    "128": "10:50",
    "130": "11:50",
    "132": "12:50",
    "134": "13:50",
    "136": "14:50",
    "138": "15:50",
    "140": "16:10",
    "142": "16:30",
    "144": "16:50",
    "146": "17:10",
    "148": "17:30",
    "150": "17:50",
    "152": "18:10",
    "154": "18:30",
    "156": "18:50",
    "158": "19:10"
  },
  "Harfield Rd": {
    "100": "05:22",
    "102": "05:47",
    "104": "06:32",
    "106": "06:52",
    "108": "07:12",
    "110": "07:32",
    "112": "07:52",
    "114": "08:12",
    "116": "08:32",
    "118": "08:47",
    "120": "09:12",
    "122": "09:32",
    "124": "09:52",
    "126": "10:12",
    "128": "10:52",
    "130": "11:52",
    "132": "12:52",
    "134": "13:52",
    "136": "14:52",
    "138": "15:52",
    "140": "16:12",
    "142": "16:32",
    "144": "16:52",
    "146": "17:12",
    "148": "17:32",
    "150": "17:52",
    "152": "18:12",
    "154": "18:32",
    "156": "18:52",
    "158": "19:12"
  },
  "Claremont": {
    "100": "05:24",
    "102": "05:49",
    "104": "06:34",
    "106": "06:54",
    "108": "07:14",
    "110": "07:34",
    "112": "07:54",
    "114": "08:14",
    "116": "08:34",
    "118": "08:49",
    "120": "09:14",
    "122": "09:34",
    "124": "09:54",
    "126": "10:14",
    "128": "10:54",
    "130": "11:54",
    "132": "12:54",
    "134": "13:54",
    "136": "14:54",
    "138": "15:54",
    "140": "16:14",
    "142": "16:34",
    "144": "16:54",
    "146": "17:14",
    "148": "17:34",
    "150": "17:54",
    "152": "18:14",
    "154": "18:34",
    "156": "18:54",
    "158": "19:14"
  },
  "Newlands": {
    "100": "05:26",
    "102": "05:51",
    "104": "06:36",
    "106": "06:56",
    "108": "07:16",
    "110": "07:36",
    "112": "07:56",
    "114": "08:16",
    "116": "08:36",
    "118": "08:51",
    "120": "09:16",
    "122": "09:36",
    "124": "09:56",
    "126": "10:16",
    "128": "10:56",
    "130": "11:56",
    "132": "12:56",
    "134": "13:56",
    "136": "14:56",
    "138": "15:56",
    "140": "16:16",
    "142": "16:36",
    "144": "16:56",
    "146": "17:16",
    "148": "17:36",
    "150": "17:56",
    "152": "18:16",
    "154": "18:36",
    "156": "18:56",
    "158": "19:16"
  },
  "Rondebosch": {
    "100": "05:28",
    "102": "05:53",
    "104": "06:38",
    "106": "06:58",
    "108": "07:18",
    "110": "07:38",
    "112": "07:58",
    "114": "08:18",
    "116": "08:38",
    "118": "08:53",
    "120": "09:18",
    "122": "09:38",
    "124": "09:58",
    "126": "10:18",
    "128": "10:58",
    "130": "11:58",
    "132": "12:58",
    "134": "13:58",
    "136": "14:58",
    "138": "15:58",
    "140": "16:18",
    "142": "16:38",
    "144": "16:58",
    "146": "17:18",
    "148": "17:38",
    "150": "17:58",
    "152": "18:18",
    "154": "18:38",
    "156": "18:58",
    "158": "19:18"
  },
  "Rosebank": {
    "100": "05:30",
    "102": "05:55",
    "104": "06:40",
    "106": "07:00",
    "108": "07:20",
    "110": "07:40",
    "112": "08:00",
    "114": "08:20",
    "116": "08:40",
    "118": "08:55",
    "120": "09:20",
    "122": "09:40",
    "124": "10:00",
    "126": "10:20",
    "128": "11:00",
    "130": "12:00",
    "132": "13:00",
    "134": "14:00",
    "136": "15:00",
    "138": "16:00",
    "140": "16:20",
    "142": "16:40",
    "144": "17:00",
    "146": "17:20",
    "148": "17:40",
    "150": "18:00",
    "152": "18:20",
    "154": "18:40",
    "156": "19:00",
    "158": "19:20"
  },
  "Mowbray": {
    "100": "05:32",
    "102": "05:57",
    "104": "06:42",
    "106": "07:02",
    "108": "07:22",
    "110": "07:42",
    "112": "08:02",
    "114": "08:22",
    "116": "08:42",
    "118": "08:57",
    "120": "09:22",
    "122": "09:42",
    "124": "10:02",
    "126": "10:22",
    "128": "11:02",
    "130": "12:02",
    "132": "13:02",
    "134": "14:02",
    "136": "15:02",
    "138": "16:02",
    "140": "16:22",
    "142": "16:42",
    "144": "17:02",
    "146": "17:22",
    "148": "17:42",
    "150": "18:02",
    "152": "18:22",
    "154": "18:42",
    "156": "19:02",
    "158": "19:22"
  },
  "Observatory": {
    "100": "05:34",
    "102": "05:59",
    "104": "06:44",
    "106": "07:04",
    "108": "07:24",
    "110": "07:44",
    "112": "08:04",
    "114": "08:24",
    "116": "08:44",
    "118": "08:59",
    "120": "09:24",
    "122": "09:44",
    "124": "10:04",
    "126": "10:24",
    "128": "11:04",
    "130": "12:04",
    "132": "13:04",
    "134": "14:04",
    "136": "15:04",
    "138": "16:04",
    "140": "16:24",
    "142": "16:44",
    "144": "17:04",
    "146": "17:24",
    "148": "17:44",
    "150": "18:04",
    "152": "18:24",
    "154": "18:44",
    "156": "19:04",
    "158": "19:24"
  },
  "Salt River": {
    "100": "05:37",
    "102": "06:02",
    "104": "06:47",
    "106": "07:07",
    "108": "07:27",
    "110": "07:47",
    "112": "08:07",
    "114": "08:27",
    "116": "08:47",
    "118": "09:02",
    "120": "09:27",
    "122": "09:47",
    "124": "10:07",
    "126": "10:27",
    "128": "11:07",
    "130": "12:07",
    "132": "13:07",
    "134": "14:07",
    "136": "15:07",
    "138": "16:07",
    "140": "16:27",
    "142": "16:47",
    "144": "17:07",
    "146": "17:27",
    "148": "17:47",
    "150": "18:07",
    "152": "18:27",
    "154": "18:47",
    "156": "19:07",
    "158": "19:27"
  },
  "Woodstock": {
    "100": "05:45",
    "102": "06:10",
    "104": "06:55",
    "106": "07:15",
    "108": "07:35",
    "110": "07:55",
    "112": "08:15",
    "114": "08:35",
    "116": "08:55",
    "118": "09:10",
    "120": "09:35",
    "122": "09:55",
    "124": "10:15",
    "126": "10:35",
    "128": "11:15",
    "130": "12:15",
    "132": "13:15",
    "134": "14:15",
    "136": "15:15",
    "138": "16:15",
    "140": "16:35",
    "142": "16:55",
    "144": "17:15",
    "146": "17:35",
    "148": "17:55",
    "150": "18:15",
    "152": "18:35",
    "154": "18:55",
    "156": "19:15",
    "158": "19:35"
  },
  "Cape Town": {
    "100": "05:48",
    "102": "06:13",
    "104": "06:58",
    "106": "07:18",
    "108": "07:38",
    "110": "07:58",
    "112": "08:18",
    "114": "08:38",
    "116": "08:58",
    "118": "09:13",
    "120": "09:38",
    "122": "09:58",
    "124": "10:18",
    "126": "10:38",
    "128": "11:18",
    "130": "12:18",
    "132": "13:18",
    "134": "14:18",
    "136": "15:18",
    "138": "16:18",
    "140": "16:38",
    "142": "16:58",
    "144": "17:18",
    "146": "17:38",
    "148": "17:58",
    "150": "18:18",
    "152": "18:38",
    "154": "18:58",
    "156": "19:18",
    "158": "19:38"
  }
}
